<annotation>
	<folder>паспорт_рф</folder>
	<filename>070941c15650a2f103ed93d9ca16c2718c493db99f539be803f70ad5726f5ee6.png</filename>
	<path>C:\Users\plaksych\PRP\dataset\train\images\паспорт_рф\070941c15650a2f103ed93d9ca16c2718c493db99f539be803f70ad5726f5ee6.png</path>
	<source>
		<database>Unknown</database>
	</source>
	<size>
		<width>768</width>
		<height>768</height>
		<depth>3</depth>
	</size>
	<segmented>0</segmented>
	<object>
		<name>cover</name>
		<pose>Unspecified</pose>
		<truncated>0</truncated>
		<difficult>0</difficult>
		<bndbox>
			<xmin>165</xmin>
			<ymin>86</ymin>
			<xmax>596</xmax>
			<ymax>696</ymax>
		</bndbox>
	</object>
</annotation>
