<annotation>
	<folder>images</folder>
	<filename>38653e142bb83b3db6c754bac558e70e25b9d77230654bfb8d70fdfcea2b58f3.png</filename>
	<path>C:\Users\plaksych\PRP\dataset\train\images\38653e142bb83b3db6c754bac558e70e25b9d77230654bfb8d70fdfcea2b58f3.png</path>
	<source>
		<database>Unknown</database>
	</source>
	<size>
		<width>1401</width>
		<height>2092</height>
		<depth>3</depth>
	</size>
	<segmented>0</segmented>
	<object>
		<name>cover</name>
		<pose>Unspecified</pose>
		<truncated>1</truncated>
		<difficult>0</difficult>
		<bndbox>
			<xmin>3</xmin>
			<ymin>11</ymin>
			<xmax>1401</xmax>
			<ymax>2092</ymax>
		</bndbox>
	</object>
</annotation>
